py_database_url/__init__.py
py_database_url/base.py
py_database_url/schemas.py
py_database_url-0.0.4.dist-info/METADATA
py_database_url-0.0.4.dist-info/RECORD
py_database_url-0.0.4.dist-info/WHEEL
py_database_url-0.0.4.dist-info/top_level.txt
