Metadata-Version: 2.1
Name: py-database-url
Version: 0.0.4
Summary: A universal database URLs for Python applications.
Home-page: https://github.com/jairojair/py-database-url
Author: Jairo Jair
Author-email: jairojair@gmail.com
License: MIT
Platform: UNKNOWN
Classifier: Intended Audience :: Developers
Classifier: License :: OSI Approved :: MIT License
Classifier: Operating System :: POSIX
Classifier: Operating System :: Microsoft :: Windows
Classifier: Operating System :: MacOS :: MacOS X
Classifier: Topic :: Utilities
Classifier: Programming Language :: Python :: 2.7
Classifier: Programming Language :: Python :: 3.6
Provides-Extra: dev
Provides-Extra: dev
Requires-Dist: pytest-cov; extra == 'dev'
Requires-Dist: pycodestyle; extra == 'dev'
Requires-Dist: black; extra == 'dev'
Requires-Dist: twine; extra == 'dev'
